LICENSE
MANIFEST.in
README.rst
setup.cfg
setup.py
docs/Button.png
docs/ComposeMails.png
docs/History.png
pretix_batch_emailer/__init__.py
pretix_batch_emailer/forms.py
pretix_batch_emailer/signals.py
pretix_batch_emailer/tasks.py
pretix_batch_emailer/urls.py
pretix_batch_emailer/views.py
pretix_batch_emailer.egg-info/PKG-INFO
pretix_batch_emailer.egg-info/SOURCES.txt
pretix_batch_emailer.egg-info/dependency_links.txt
pretix_batch_emailer.egg-info/entry_points.txt
pretix_batch_emailer.egg-info/top_level.txt
pretix_batch_emailer/locale/django.pot
pretix_batch_emailer/locale/de/LC_MESSAGES/django.mo
pretix_batch_emailer/locale/de/LC_MESSAGES/django.po
pretix_batch_emailer/locale/de_Informal/LC_MESSAGES/django.po
pretix_batch_emailer/locale/de_informal/LC_MESSAGES/django.mo
pretix_batch_emailer/locale/de_informal/LC_MESSAGES/django.po
pretix_batch_emailer/static/pretix_batch_emailer/.gitkeep
pretix_batch_emailer/static/pretix_batch_emailer/batch-emailer.js
pretix_batch_emailer/templates/pretix_batch_emailer/.gitkeep
pretix_batch_emailer/templates/pretix_batch_emailer/collect_bulk_orders.html
pretix_batch_emailer/templates/pretix_batch_emailer/history.html
pretix_batch_emailer/templates/pretix_batch_emailer/send_mail.html