Metadata-Version: 1.0
Name: pretix-batch-emailer
Version: 1.0.1
Summary: Send a Batch Email to all currently displayed orders.
Home-page: https://github.com/bockstaller/pretix-batch-emailer
Author: Lukas Bockstaller
Author-email: lukas.bockstaller@posteo.de
License: Apache
Platform: UNKNOWN
